learnupon/__init__.py
learnupon/client.py
learnupon-0.2.0.dist-info/WHEEL
learnupon-0.2.0.dist-info/METADATA
learnupon-0.2.0.dist-info/RECORD
