Metadata-Version: 2.1
Name: learnupon
Version: 0.2.0
Summary: 
Home-page: https://github.com/swimlane/swimlane-learnupon
Author: Michael Butler
Author-email: michael.butler@swimlane.com
Requires-Python: >=3.6,<4.0
Classifier: Programming Language :: Python :: 3
Classifier: Programming Language :: Python :: 3.6
Classifier: Programming Language :: Python :: 3.7
Requires-Dist: requests (>=2.22,<3.0)
Project-URL: Repository, https://github.com/swimlane/swimlane-learnupon
